{
  "$schema": "https://developer.microsoft.com/json-schemas/spfx-build/package-solution.schema.json",
  "solution": {
    "name": "project-management-web-part-client-side-solution",
    "id": "d5e54f4b-5ccc-405c-b66f-ed58765745e9",
    "version": "1.0.0.8",
    "includeClientSideAssets": true,
    "skipFeatureDeployment": true,
    "isDomainIsolated": false,
    "developer": {
      "name": "",
      "websiteUrl": "",
      "privacyUrl": "",
      "termsOfUseUrl": "",
      "mpnId": ""
    },
    "webApiPermissionRequests": [{
        "resource": "Windows Azure Active Directory",
        "scope": "User.Read.All"
      },
      {
        "resource": "Microsoft Graph",
        "scope": "User.ReadBasic.All"
      }, {
        "resource": "Microsoft Graph",
        "scope": "Group.Read.All"
      }, {
        "resource": "Microsoft Graph",
        "scope": "User.Read.All"
      }, {
        "resource": "Microsoft Graph",
        "scope": "Directory.Read.All"
      }, {
        "resource": "Microsoft Graph",
        "scope": "GroupMember.ReadWrite.All"
      }, {
        "resource": "Microsoft Graph",
        "scope": "Group.ReadWrite.All"
      }, {
        "resource": "Microsoft Graph",
        "scope": "Directory.ReadWrite.All"
      }
    ]
  },
  "paths": {
    "zippedPackage": "solution/project-management-web-part.sppkg"
  }
}
